[
  {
    "url": "https://youtu.be/skTRV6yM-Js?si=xx48CaXKMSZfGm54",
    "title": "اشياء لا تشتريها اذا كنت جيمر مطفر",
    "status": "Completed",
    "timestamp": "2025-08-27T05:39:53.297440",
    "file_path": "D:/%(title)s.%(ext)s",
    "duration": "03:21"
  },
  {
    "url": "https://youtu.be/skTRV6yM-Js?si=xx48CaXKMSZfGm54",
    "title": "اشياء لا تشتريها اذا كنت جيمر مطفر",
    "status": "Completed",
    "timestamp": "2025-08-27T05:40:55.142472",
    "file_path": "D:/%(title)s.%(ext)s",
    "duration": "03:21"
  },
  {
    "url": "https://youtu.be/skTRV6yM-Js?si=xx48CaXKMSZfGm54",
    "title": "اشياء لا تشتريها اذا كنت جيمر مطفر",
    "status": "Completed",
    "timestamp": "2025-08-27T05:41:52.184681",
    "file_path": "D:/%(title)s.%(ext)s",
    "duration": "03:21"
  }
]